json2c.py
setup.py
json2c.egg-info/PKG-INFO
json2c.egg-info/SOURCES.txt
json2c.egg-info/dependency_links.txt
json2c.egg-info/entry_points.txt
json2c.egg-info/top_level.txt