Metadata-Version: 1.0
Name: json2c
Version: 0.9.1
Summary: Convert JSON to C data literals
Home-page: https://github.com/orangeduck/json2c
Author: Daniel Holden
Author-email: contact@theorangeduck.com
License: BSD
Platform: UNKNOWN
